pyqt_music_player_widget/__init__.py
pyqt_music_player_widget/musicPlayerWidget.py
pyqt_music_player_widget/ico/__init__.py
pyqt_music_player_widget/ico/pause.svg
pyqt_music_player_widget/ico/play.svg
pyqt_music_player_widget/ico/stop.svg
pyqt_music_player_widget-0.0.2.dist-info/LICENSE
pyqt_music_player_widget-0.0.2.dist-info/METADATA
pyqt_music_player_widget-0.0.2.dist-info/WHEEL
pyqt_music_player_widget-0.0.2.dist-info/top_level.txt
pyqt_music_player_widget-0.0.2.dist-info/RECORD
