Metadata-Version: 2.1
Name: pyqt-music-player-widget
Version: 0.0.2
Summary: PyQt music player widget
Home-page: https://github.com/yjg30737/pyqt-music-player-widget.git
Author: Jung Gyu Yoon
Author-email: yjg30737@gmail.com
License: MIT
License-File: LICENSE
Requires-Dist: PyQt5 (>=5.8)
Requires-Dist: mutagen (>=1.45.1)
Requires-Dist: pyqt-media-slider (>=0.0.1)
Requires-Dist: pyqt-svg-button (>=0.0.1)
